smart_str/__init__.py
smart_str/code_point.py
smart_str/smart_char.py
smart_str/smart_str.py
smart_str/smart_str_constants.py
smart_str/example/__init__.py
smart_str/example/smart_str_example.py
smart_str/tests/__init__.py
smart_str/tests/test_code_point.py
smart_str/tests/test_smart_char.py
smart_str/tests/test_smart_str.py
smart_string-0.0.10.dist-info/DESCRIPTION.rst
smart_string-0.0.10.dist-info/METADATA
smart_string-0.0.10.dist-info/RECORD
smart_string-0.0.10.dist-info/WHEEL
smart_string-0.0.10.dist-info/metadata.json
smart_string-0.0.10.dist-info/top_level.txt
