Metadata-Version: 2.0
Name: smart-string
Version: 0.0.10
Summary: Smart String implementation
Home-page: https://github.com/markk2504/smart-string
Author: Mark Kaplan
Author-email: markk2504@gmail.com
License: MIT
Platform: UNKNOWN
Classifier: Development Status :: 3 - Alpha
Classifier: Intended Audience :: Developers
Classifier: Topic :: Software Development :: Libraries :: Python Modules
Classifier: License :: OSI Approved :: MIT License
Classifier: Programming Language :: Python :: 2.7
Requires-Python: ==2.7.*
Requires-Dist: enum34
